few_shot_priming/__init__.py
few_shot_priming/baseline.py
few_shot_priming/conf.yaml
few_shot_priming/config.py
few_shot_priming/experiments.py
few_shot_priming/ibm_baseline.py
few_shot_priming/in_context_finetuning.py
few_shot_priming/instructional_finetuning.py
few_shot_priming/mylogging.py
few_shot_priming/prompt_fine_tuning.py
few_shot_priming/prompting_stance.py
few_shot_priming/utils.py
few_shot_priming/argument_sampling/__init__.py
few_shot_priming/argument_sampling/diversify.py
few_shot_priming/argument_sampling/sampling_strategies.py
few_shot_priming/argument_sampling/stance_priming.py
few_shot_priming/argument_sampling/topic_similarity.py
few_shot_priming/argument_sampling/topic_similarity_sentence_transformer.py
few_shot_priming/data/alpaca.json
few_shot_priming/data/claim_stance_dataset_v1.csv
few_shot_priming/data/mistral.json
few_shot_priming/data/place-holder.txt
few_shot_priming/data/vicuna.json
few_shot_priming-0.3.950.dist-info/METADATA
few_shot_priming-0.3.950.dist-info/WHEEL
few_shot_priming-0.3.950.dist-info/top_level.txt
few_shot_priming-0.3.950.dist-info/RECORD
