Metadata-Version: 2.4
Name: few_shot_priming
Version: 0.3.950
Summary: Analyzing priming effects in a few shot setting environment
Home-page: https://gitlab.uni-hannover.de/y.ajjour/few-shot-priming
Author: Yamen Ajjour
Author-email: yajjour@hotmail.com
Classifier: Programming Language :: Python :: 3
Classifier: License :: OSI Approved :: MIT License
Classifier: Operating System :: OS Independent
Dynamic: author
Dynamic: author-email
Dynamic: classifier
Dynamic: description
Dynamic: description-content-type
Dynamic: home-page
Dynamic: summary
